python_app_template_starter/__init__.py
python_app_template_starter/__main__.py
python_app_template_starter/cli.py
python_app_template_starter/config.py
python_app_template_starter-0.1.0.dist-info/licenses/LICENSE
python_app_template_starter-0.1.0.dist-info/METADATA
python_app_template_starter-0.1.0.dist-info/WHEEL
python_app_template_starter-0.1.0.dist-info/entry_points.txt
python_app_template_starter-0.1.0.dist-info/top_level.txt
python_app_template_starter-0.1.0.dist-info/RECORD
